uisdata/__init__.py
uisdata/bdds.py
uisdata-0.1.dist-info/LICENSE
uisdata-0.1.dist-info/METADATA
uisdata-0.1.dist-info/WHEEL
uisdata-0.1.dist-info/top_level.txt
uisdata-0.1.dist-info/RECORD
