Metadata-Version: 2.1
Name: uisdata
Version: 0.1
Summary: Consumes the UIS Bulk Data Download System (BDDS): get, select, subset, merge metadata/labels, search, other utilities
Home-page: https://github.com/Maxime-Murphy/uisdata
Author: Maxime Murphy
Author-email: maxime.murphy@gmail.com
Classifier: Programming Language :: Python :: 3
Classifier: License :: OSI Approved :: MIT License
Classifier: Operating System :: OS Independent
Classifier: Development Status :: 4 - Beta
Classifier: Intended Audience :: Science/Research
Classifier: Topic :: Database
Classifier: Topic :: Scientific/Engineering :: Information Analysis
Requires-Python: >=3.6
License-File: LICENSE
Requires-Dist: pandas
Requires-Dist: requests
Requires-Dist: numpy
